dast/__init__.py
dast/__main__.py
dast/from_ast.py
dast/lcs.py
dast/pprint.py
dast-0.0.29.dist-info/METADATA
dast-0.0.29.dist-info/WHEEL
dast-0.0.29.dist-info/top_level.txt
dast-0.0.29.dist-info/RECORD
