Metadata-Version: 2.1
Name: dast
Version: 0.0.29
Summary: UNKNOWN
Home-page: UNKNOWN
Author: Marco Caselli, Will Lohrmann
License: UNKNOWN
Platform: UNKNOWN
Requires-Dist: deepdiff
